testing_pypi/__init__.py
testing_pypi/__main__.py
testing_pypi/calc.sh
testing_pypi/test_func.py
testing_pypi-6.0.dist-info/LICENSE
testing_pypi-6.0.dist-info/WHEEL
testing_pypi-6.0.dist-info/METADATA
testing_pypi-6.0.dist-info/RECORD
